COPYING.txt
MANIFEST.in
README.rst
setup.py
httplog/__init__.py
httplog/__init__.pyc
httplog/base.py
httplog/base.pyc
httplog/decorators.py
httplog/decorators.pyc
httplog/filters.py
httplog/filters.pyc
httplog/middleware.py
httplog/middleware.pyc
httplog/serializers.py
httplog/serializers.pyc
httplog/services.py
httplog/services.pyc
httplog/tasks.py
httplog/tasks.pyc
httplog/urls.py
httplog/urls.pyc
httplog/views.py
httplog/views.pyc
httplog.egg-info/PKG-INFO
httplog.egg-info/SOURCES.txt
httplog.egg-info/dependency_links.txt
httplog.egg-info/pbr.json
httplog.egg-info/top_level.txt
httplog.egg-info/zip-safe
httplog/.idea/httplog.iml
httplog/.idea/misc.xml
httplog/.idea/modules.xml
httplog/.idea/workspace.xml
httplog/migrations/0001_initial.py
httplog/migrations/0001_initial.pyc
httplog/migrations/__init__.py
httplog/migrations/__init__.pyc
httplog/models/__init__.py
httplog/models/__init__.pyc
httplog/models/httplog.py
httplog/models/httplog.pyc