Metadata-Version: 1.1
Name: httplog
Version: 1.2.0
Summary: this is a test package for extract http log.
Home-page: https://github.com/mkloveyy/httplog
Author: ma_k
Author-email: ma_k@ctrip.com
License: MIT
Keywords: test http log
Platform: UNKNOWN
Classifier: License :: OSI Approved :: MIT License
Classifier: Framework :: Django
Classifier: Programming Language :: Python :: 2.7
Classifier: Intended Audience :: Developers
Classifier: Operating System :: OS Independent
